{
  "name": {
    "tr": "Çene Estetiği",
    "en": "Chin Surgery",
    "ar": "تجميل الذقن",
    "ru": "Пластика подбородка",
    "de": "Kinnkorrektur"
  },
  "status": "play",
  "category": "estetik-uygulamalar",
  "id": "cene-estetigi",
  "path": "cene-estetigi",
  "index": 2,
  "desing": {
    "header": [],
    "body": [],
    "footer": []
  },
  "description": {
    "tr": "Çene ucunu yeniden şekillendiren, yüz oranlarını dengeleyen cerrahi işlemler.",
    "en": "Surgical procedures that reshape the chin tip and balance facial proportions.",
    "ar": "العمليات الجراحية التي تعيد تشكيل طرف الذقن وتوازن نسب الوجه.",
    "ru": "Хирургические процедуры, изменяющие форму кончика подбородка и гармонизирующие пропорции лица.",
    "de": "Chirurgische Eingriffe, die die Kinnspitze neu formen und die Gesichtsproportionen ausgleichen."
  },
  "keyword": {
    "tr": "çene estetiği, genioplasti, çene küçültme",
    "en": "chin surgery, genioplasty, chin reduction",
    "ar": "تجميل الذقن، جينوبلاستي، تصغير الذقن",
    "ru": "пластика подбородка, гениопластика, уменьшение подбородка",
    "de": "Kinn-OP, Genioplastik, Kinnverkleinerung"
  },
  "spot": {
    "tr": "Alt yüz hattı, profilde dengeli bir görünüm kazanır.",
    "en": "The lower facial line gains a balanced appearance in profile.",
    "ar": "يتحسن مظهر الوجه السفلي بشكل متوازن في المظهر الجانبي.",
    "ru": "Линия нижней части лица приобретает сбалансированный вид в профиль.",
    "de": "Die untere Gesichtslinie erhält im Profil ein ausgewogenes Erscheinungsbild."
  },
  "text": {
    "tr": "<h2>Çene Estetiği (Genioplasti)</h2><p>Çene estetiği, alt yüzün orantılarını düzenleyerek profilde dengeli bir görünüm elde etmeye yardımcı olur. Op. Dr. Saffet Ulutaş, çene ucunun yetersiz projeksiyonunu düzeltmek, genişliği dengelemek veya asimetrileri gidermek için genioplasti operasyonlarını kişiye özel planlar. İlk incelemede diş yapısı, çiğneme fonksiyonu, çene eklemi sağlığı ve dudak kapanışı değerlendirilir; gerekirse ortodonti uzmanlarıyla multidisipliner çalışma yürütülür.</p><p>Genioplasti sırasında çene ucu kemiği kontrollü biçimde kesilerek öne, arkaya, aşağı veya yukarı doğru yeniden konumlandırılır. Bu işlem sırasında hassas ölçümler yapılır ve titanyum plaklar kullanılarak yeni konum sabitlenir. Bazı vakalarda implant veya yağ enjeksiyonu desteğiyle kontur daha da belirginleştirilir. Op. Dr. Ulutaş, yüz estetiğinde alt yüzün feminen veya maskülen çizgilerine dikkat ederek kişiye uygun sonuçlar hedefler.</p><p>Ameliyat sonrası dönem, yumuşak doku iyileşmesini destekleyen beslenme planları ve özel bandajlarla kontrol altında tutulur. Çene hareketlerini sınırlayan ağrılar için ilaç desteği verilir; şişliklerin azalması için manuel lenf drenajı ve soğuk uygulamalar önerilir. Ortalama 1-2 hafta içinde günlük yaşama dönüş mümkün olurken, nihai kontur 3-4 ay içinde oturur.</p><p>Çene estetiği yalnızca profili güzelleştirmekle kalmaz; çene hattının keskinliği boyun bölgesindeki sarkma izlenimini azaltır ve diş yapısının görünürlüğünü dengeler. Jawline dolgusu veya boyun germe gibi kombine işlemlerle toplam yüz estetiği güçlendirilir. Dr. Saffet Ulutaş, ameliyat öncesi 3 boyutlu planlama araçlarıyla muhtemel sonuçları hastalarıyla paylaşır, bu sayede operasyon sonrası sürprizler en aza indirilir.</p><p>Gaziantep’te çene estetiği düşünen hastalar için güvenilir bir cerrahi ekip ve detaylı takip süreci kritik önem taşır. Kliniğimiz, her aşamada şeffaf bilgilendirme ve kişisel ihtiyaçlara uygun tasarım felsefesiyle hizmet verir. Alt yüzünüzdeki dengeyi yeniden kurmak için Op. Dr. Saffet Ulutaş ile görüşebilir, size özel genioplasti planınızı belirleyebilirsiniz.</p>",
    "en": "<h2>Chin Aesthetic (Genioplasty)</h2><p>Chin surgery helps to obtain a balanced appearance in profile by arranging the proportions of the lower face. Op. Dr. Saffet Ulutaş plans genioplasty operations personally to correct improper projection of the chin tip, balance the width, or eliminate asymmetries. In the first examination, dental structure, chewing function, jaw joint health, and lip closure are evaluated; if necessary, multidisciplinary work is carried out with orthodontists.</p><p>During genioplasty, the chin tip bone is controlledly cut and repositioned forward, backward, down, or up. Precise measurements are made during this procedure, and the new position is fixed using titanium plates. In some cases, the contour is further sharpened with implant or fat injection support. Op. Dr. Ulutaş aims for results suitable for the person by paying attention to the feminine or masculine lines of the lower face in facial aesthetics.</p><p>The post-operative period is kept under control with nutrition plans and special bandages that support soft tissue healing. Medication support is given for pains that limit chin movements; manual lymph drainage and cold applications are recommended for swelling to decrease. While it is possible to return to daily life within 1-2 weeks on average, the final contour settles within 3-4 months.</p><p>Chin surgery not only beautifies the profile; the sharpness of the jawline reduces the impression of sagging in the neck area and balances the visibility of the tooth structure. Total facial aesthetics are strengthened with combined procedures such as jawline filling or neck lift. Dr. Saffet Ulutaş shares probable results with his patients with 3D planning tools before surgery, so surprises after surgery are minimized.</p>",
    "ar": "<h2>تجميل الذقن (جينوبلاستي)</h2><p>يساعد تجميل الذقن في الحصول على مظهر متوازن للملف الجانبي من خلال ترتيب نسب الوجه السفلي. يخطط الدكتور صافيت أولوتاش لعمليات تجميل الذقن بشكل شخصي لتصحيح البروز غير الكافي لطرف الذقن، أو موازنة العرض، أو القضاء على عدم التماثل. في الفحص الأول، يتم تقييم بنية الأسنان، ووظيفة المضغ، وصحة مفصل الفك، وإغلاق الشفاه؛ وإذا لزم الأمر، يتم إجراء عمل متعدد التخصصات مع أخصائيي تقويم الأسنان.</p><p>أثناء عملية تجميل الذقن، يتم قطع عظم طرف الذقن بشكل محكم وإعادة وضعه للأمام أو للخلف أو للأسفل أو للأعلى. يتم إجراء قياسات دقيقة خلال هذا الإجراء، ويتم تثبيت الوضع الجديد باستخدام صفائح التيتانيوم. في بعض الحالات، يتم إبراز المخطط بشكل أكبر باستخدام الغرسات أو دعم حقن الدهون. يهدف الدكتور أولوتاش لنتائج مناسبة للشخص من خلال الاهتمام بالخطوط الأنثوية أو الذكورية للوجه السفلي في جماليات الوجه.</p>",
    "ru": "<h2>Пластика подбородка (Гениопластика)</h2><p>Пластика подбородка помогает достичь сбалансированного профиля, корректируя пропорции нижней части лица. Оп. Д-р Саффет Улуташ индивидуально планирует операции по гениопластике для коррекции недостаточной проекции кончика подбородка, балансировки его ширины или устранения асимметрии. При первичном осмотре оцениваются структура зубов, жевательная функция, здоровье челюстного сустава и смыкание губ; при необходимости проводится мультидисциплинарная работа совместно с ортодонтами.</p>",
    "de": "<h2>Kinnkorrektur (Genioplastik)</h2><p>Eine Kinnkorrektur hilft dabei, ein ausgewogenes Profil zu erzielen, indem die Proportionen des unteren Gesichts angepasst werden. Op. Dr. Saffet Ulutaş plant Genioplastik-Operationen individuell, um eine unzureichende Projektion der Kinnspitze zu korrigieren, die Breite auszugleichen oder Asymmetrien zu beseitigen. Bei der Erstuntersuchung werden Zahnstruktur, Kaufunktion, Kiefergelenkgesundheit und Lippenschluss bewertet; falls erforderlich, erfolgt eine multidisziplinäre Zusammenarbeit mit Kieferorthopäden.</p>"
  },
  "update": "2026-02-02T16:04:48.567Z",
  "date": "2025-11-12T01:14:00.000Z"
}