{
  "name": {
    "tr": "Kullanıcı Hakları"
  },
  "status": "play",
  "id": "kullanicahaklari",
  "path": "kullanici-haklari",
  "category": "",
  "text": {
    "tr": "<h2>Hasta ve Kullanıcı Hakları</h2>\n<p>Hastalarımızın tüm haklarına saygı duymak, verdiğimiz sağlık hizmetlerinin temelini oluşturur. Op. Dr. Saffet Ulutaş kliniğinde herkes; bilgilendirilme, onam, mahremiyet ve itiraz haklarını özgürce kullanabilir. Tedavi öncesi tüm süreçler anlaşılır bir dille anlatılır, alternatif seçenekler ve olası riskler detaylandırılır. Hastalarımız sorularını çekinmeden sorabilir, kararlarını özgür iradeleriyle verir.</p>\n<p>Bilgilendirilmiş onam, her operasyon veya medikal işlem öncesinde yazılı olarak alınır. Onam formu, prosedürün amacı, süresi, riskleri ve beklenen faydaları içerecek şekilde hazırlanır. Hastalarımız dilerse işlemden vazgeçme veya erteleme hakkını kullanabilir. Reşit olmayan veya kendini ifade edemeyen kişilerin hakları yasal temsilcileri aracılığıyla korunur.</p>\n<p>Mahremiyet ve veri koruma hakları, kullanıcı haklarımızın önemli bir parçasıdır. Hasta odaları ve muayene alanları, kişisel bilgilerinizin gizli kalmasını sağlayacak şekilde düzenlenmiştir. Fotoğraf ve video kayıtları yalnızca izin dahilinde kullanılır. Kliniğimiz, engelli bireylerin haklarına da hassasiyet göstererek erişilebilirlik düzenlemeleri yapar.</p>\n<p>Geri bildirim ve şikâyet süreçleri şeffaftır. Her hastaya iletişim kanalları anlatılır; çağrı merkezi, e-posta ve yüz yüze görüşme seçenekleri sunulur. Gelen her geri bildirim kalite ekibi tarafından incelenir, çözüm süresi hastaya bildirilir. Böylece hizmetlerimizi sürekli geliştirmek ve haklara saygılı kalmak mümkün olur.</p>\n<p>Op. Dr. Saffet Ulutaş kliniği, hasta hakları konusunda sorumluluk bilinciyle hareket eder. Sağlık hizmeti alan herkesin kendini güvende, anlaşılmış ve değer verilmiş hissetmesi için elimizden geleni yaparız. Sorularınız veya talepleriniz için dilediğiniz zaman bizimle iletişime geçebilirsiniz.</p>"
  },
  "desing": {
    "header": [],
    "body": [],
    "footer": []
  },
  "desc": {},
  "index": 6,
  "icon": "home",
  "description": {
    "tr": "Bilgilendirilmiş onam, veri erişimi ve geri bildirim haklarınızı açıklayan rehber."
  },
  "keyword": {
    "tr": "hasta hakları estetik klinik, bilgilendirilmiş onam"
  },
  "spot": {
    "tr": "Her hasta bilgilendirilme ve onam hakkını kullanır."
  },
  "update": "2025-11-12T02:42:00.000Z",
  "date": "2025-11-12T01:13:52.000Z"
}