{
  "name": {
    "tr": "Estetik Uygulamalar",
    "en": "",
    "ar": "",
    "ru": "",
    "de": ""
  },
  "status": "play",
  "category": "",
  "id": "estetik-uygulamalar",
  "path": "estetik-uygulamalar",
  "index": 0,
  "desing": {
    "header": [],
    "body": [],
    "footer": []
  },
  "description": {
    "tr": "Burun, yüz, vücut ve kulak estetiğini kapsayan kapsamlı cerrahi çözümler.",
    "en": "",
    "ar": "",
    "ru": "",
    "de": ""
  },
  "spot": {
    "tr": "Doğal görünüme sadık kalarak kişiye özel estetik planlama yapılır.",
    "en": "",
    "ar": "",
    "ru": ""
  },
  "desc": {},
  "icon": "home",
  "img": "dtygq.png",
  "keyword": {
    "tr": "",
    "en": "",
    "ar": "",
    "ru": "",
    "de": ""
  },
  "text": {
    "tr": "",
    "en": "",
    "ar": "",
    "ru": "",
    "de": ""
  },
  "update": "2026-02-02T09:58:17.170Z",
  "date": "2025-11-17T23:59:21.481Z"
}