{
  "name": {
    "tr": "İletişim",
    "en": "",
    "ar": "",
    "ru": ""
  },
  "status": "play",
  "category": "",
  "id": "iletisim",
  "path": "i-letisim",
  "index": 5,
  "desing": {
    "header": [],
    "body": [
      "ic3ufe",
      "aqp22u"
    ],
    "footer": []
  },
  "description": {
    "tr": "Randevu talebi, iletişim formu ve sosyal medya kanalları üzerinden kliniğe ulaşım seçenekleri.",
    "en": "",
    "ar": "",
    "ru": ""
  },
  "spot": {
    "tr": "Telefon, WhatsApp ve sosyal medya hesapları üzerinden hızlı iletişim ve randevu planlaması yapılır.",
    "en": "",
    "ar": "",
    "ru": ""
  },
  "desc": {},
  "keyword": {
    "tr": "",
    "en": "",
    "ar": "",
    "ru": ""
  },
  "text": {
    "tr": "<h2>İletişim ve Randevu</h2>\n<p>Op. Dr. Saffet Ulutaş kliniği, Gaziantep’in merkezinde kolay ulaşılabilir bir konumda hizmet verir. Estetik cerrahi, medikal estetik, rekonstrüktif cerrahi veya danışmanlık talepleriniz için haftanın her günü bilgi alabilirsiniz. Randevu takvimimizi yoğunluğa rağmen esnek tutmaya özen gösteriyor, şehir dışından gelen hastalarımızın uçuş saatlerine göre planlama yapıyoruz.</p>\n<p>Kliniğimizle iletişime geçmek için telefon hattımızdan, WhatsApp destek numaramızdan veya web sitemizdeki form aracılığıyla mesaj gönderebilirsiniz. WhatsApp üzerinden paylaştığınız sorular, fotoğraflar ve tetkikler gizlilik sözleşmemiz kapsamında korunur. İlk değerlendirmenin ardından sizi muayeneye davet eder veya çevrimiçi görüşme organize ederiz. Sağlık turizmi kapsamındaki misafirlerimiz için konaklama ve transfer desteği sunan çözüm ortaklarımız hazırdır.</p>\n<p>Adresimiz ve konum bilgimiz, randevu onayı sırasında SMS ve e-posta yoluyla paylaşılır. Kliniğimizde otopark, engelli erişimi ve ferah bekleme alanları bulunur. Muayene öncesinde kimlik bilgilerinizin yanınızda olması, daha hızlı kayıt açmamıza yardımcı olur. Refakatçi ile gelmeniz halinde danışma ekibimiz konforlu bir bekleme düzeni sağlar.</p>\n<p>Danışan memnuniyetini artırmak amacıyla her görüşme sonrası geri bildirim toplarız. Görüş, öneri veya şikâyetlerinizi iletmek için 7/24 açık iletişim kanallarımızı kullanabilirsiniz. Op. Dr. Saffet Ulutaş ve ekibi, ameliyat öncesi ve sonrası süreçte sizinle sürekli irtibat halinde kalır; ilaç düzeni, yara bakımı ve kontrol randevuları titizlikle takip edilir.</p>\n<p>Estetik cerrahi yolculuğunuzun her aşamasında kendinizi güvende hissetmeniz için yanınızdayız. Ortalama dönüş süremiz mesai saatleri içinde 30 dakikanın altındadır. Mesai dışı mesajlarınız ilk iş gününde yanıtlanır. Bizimle iletişime geçmek için telefonla arayabilir, WhatsApp üzerinden yazabilir veya info@drsaffetulutas.com adresine e-posta gönderebilirsiniz.</p>",
    "en": "",
    "ar": "",
    "ru": ""
  },
  "update": "2025-11-18T00:04:07.294Z",
  "date": "2025-11-12T00:58:10.678Z",
  "pathnext": ""
}